setup.py
src/digimat/__init__.py
src/digimat.unigeweather.egg-info/PKG-INFO
src/digimat.unigeweather.egg-info/SOURCES.txt
src/digimat.unigeweather.egg-info/dependency_links.txt
src/digimat.unigeweather.egg-info/namespace_packages.txt
src/digimat.unigeweather.egg-info/not-zip-safe
src/digimat.unigeweather.egg-info/requires.txt
src/digimat.unigeweather.egg-info/top_level.txt
src/digimat/unigeweather/__init__.py
src/digimat/unigeweather/unige.py