Metadata-Version: 1.1
Name: digimat.unigeweather
Version: 0.1.7
Summary: Digimat UNIGE weather data access
Home-page: http://www.digimat.ch
Author: Frederic Hess
Author-email: fhess@st-sa.ch
License: PSF
Platform: UNKNOWN
Classifier: Development Status :: 4 - Beta
Classifier: Programming Language :: Python :: 3
